appium_mcp/__init__.py
appium_mcp/cli.py
appium_mcp/server.py
appium_mcp/core/__init__.py
appium_mcp/core/config_manager.py
appium_mcp/core/device_manager.py
appium_mcp/core/prompt_manager.py
appium_mcp/core/resource_manager.py
appium_mcp/core/session_manager.py
appium_mcp/tools/__init__.py
appium_mcp/tools/base.py
appium_mcp/tools/device_tools.py
appium_mcp/tools/ui_tools.py
appium_mcp/utils/__init__.py
appium_mcp/utils/exceptions.py
appium_mcp/utils/helpers.py
iflow_mcp_1405942836_appium_mcp_server-1.0.0.dist-info/licenses/LICENSE
iflow_mcp_1405942836_appium_mcp_server-1.0.0.dist-info/METADATA
iflow_mcp_1405942836_appium_mcp_server-1.0.0.dist-info/WHEEL
iflow_mcp_1405942836_appium_mcp_server-1.0.0.dist-info/entry_points.txt
iflow_mcp_1405942836_appium_mcp_server-1.0.0.dist-info/top_level.txt
iflow_mcp_1405942836_appium_mcp_server-1.0.0.dist-info/RECORD
