Metadata-Version: 2.4
Name: iflow-mcp_1405942836_appium-mcp-server
Version: 1.0.0
Summary: Appium MCP Server - Mobile automation testing via Model Context Protocol
Author-email: Appium MCP Team <contact@appium-mcp.com>
License: MIT
Project-URL: Homepage, https://github.com/1405942836/appium-mcp
Project-URL: Documentation, https://github.com/1405942836/appium-mcp/tree/main/docs
Project-URL: Repository, https://github.com/1405942836/appium-mcp.git
Project-URL: Issues, https://github.com/1405942836/appium-mcp/issues
Keywords: appium,mcp,mobile,automation,testing
Classifier: Development Status :: 4 - Beta
Classifier: Intended Audience :: Developers
Classifier: License :: OSI Approved :: MIT License
Classifier: Programming Language :: Python :: 3
Classifier: Programming Language :: Python :: 3.9
Classifier: Programming Language :: Python :: 3.10
Classifier: Programming Language :: Python :: 3.11
Classifier: Programming Language :: Python :: 3.12
Classifier: Topic :: Software Development :: Testing
Classifier: Topic :: Software Development :: Quality Assurance
Requires-Python: >=3.9
License-File: LICENSE
Requires-Dist: mcp>=1.12.0
Requires-Dist: Appium-Python-Client>=4.0.0
Requires-Dist: pydantic>=2.0.0
Requires-Dist: pyyaml>=6.0.0
Requires-Dist: click>=8.0.0
Requires-Dist: structlog>=23.0.0
Requires-Dist: aiofiles>=23.0.0
Requires-Dist: pillow>=10.0.0
Provides-Extra: dev
Requires-Dist: pytest>=7.0.0; extra == "dev"
Requires-Dist: pytest-asyncio>=0.21.0; extra == "dev"
Requires-Dist: pytest-cov>=4.0.0; extra == "dev"
Requires-Dist: black>=23.0.0; extra == "dev"
Requires-Dist: isort>=5.12.0; extra == "dev"
Requires-Dist: flake8>=6.0.0; extra == "dev"
Requires-Dist: mypy>=1.0.0; extra == "dev"
Requires-Dist: pre-commit>=3.0.0; extra == "dev"
Provides-Extra: monitoring
Requires-Dist: prometheus-client>=0.19.0; extra == "monitoring"
Requires-Dist: psutil>=5.9.0; extra == "monitoring"
Provides-Extra: security
Requires-Dist: cryptography>=41.0.0; extra == "security"
Requires-Dist: pyjwt>=2.8.0; extra == "security"
Dynamic: license-file
